PyDPFT/__init__.py
PyDPFT/plot.py
PyDPFT-1.0.6.dist-info/LICENSE.txt
PyDPFT-1.0.6.dist-info/METADATA
PyDPFT-1.0.6.dist-info/WHEEL
PyDPFT-1.0.6.dist-info/top_level.txt
PyDPFT-1.0.6.dist-info/RECORD
