Metadata-Version: 2.1
Name: PyDPFT
Version: 1.0.6
Summary: A package for density potential functional theory
Home-page: https://github.com/tesla-cat/PyDPFT
Author: Ding Ruiqi
Author-email: 416640656@qq.com
License: UNKNOWN
Platform: UNKNOWN
Classifier: Programming Language :: Python :: 3
Classifier: License :: OSI Approved :: MIT License
Classifier: Operating System :: OS Independent
Requires-Python: >=3.6
